ltr.libs/libgomp-ad058278.so.1.0.0
ranky/__init__.py
ranky/git_info.py
ranky/about.py
ranky/learning/__init__.py
ranky/aggregation/__init__.py
ranky/aggregation/unsupervised.pxd
ranky/aggregation/unsupervised.cpp
ranky/aggregation/unsupervised.cpython-38-x86_64-linux-gnu.so
ranky/aggregation/unsupervised.pyx
ranky/primitives/datapoint.cpython-38-x86_64-linux-gnu.so
ranky/primitives/__init__.py
ranky/primitives/ranklist.pxd
ranky/primitives/ranklist.pyx
ranky/primitives/datapoint.cpp
ranky/primitives/datapoint.pyx
ranky/primitives/datapoint.pxd
ranky/utils/__init__.py
ranky/metric/__init__.py
ltr-0.0.2.dist-info/LICENSE
ltr-0.0.2.dist-info/METADATA
ltr-0.0.2.dist-info/RECORD
ltr-0.0.2.dist-info/WHEEL
ltr-0.0.2.dist-info/top_level.txt
tests/__init__.py
tests/test_datapoint.py
