Metadata-Version: 2.1
Name: ltr
Version: 0.0.2
Summary: A fast Learning to Rank library based on RankLib
Home-page: https://marcosfpr.github.io
Author: MatchUp
Author-email: mfprezende@gmail.com
License: MIT
Project-URL: Release notes, https://github.com/matchup-ir/ranky/releases
Project-URL: Source, https://github.com/matchup-ir/ranky
Platform: UNKNOWN
Classifier: Development Status :: 1 - Planning
Classifier: Environment :: Console
Classifier: Intended Audience :: Developers
Classifier: Intended Audience :: Science/Research
Classifier: License :: OSI Approved :: MIT License
Classifier: Operating System :: POSIX :: Linux
Classifier: Operating System :: MacOS :: MacOS X
Classifier: Operating System :: Microsoft :: Windows
Classifier: Programming Language :: Cython
Classifier: Programming Language :: Python :: 3
Classifier: Programming Language :: Python :: 3.6
Classifier: Programming Language :: Python :: 3.7
Classifier: Programming Language :: Python :: 3.8
Classifier: Programming Language :: Python :: 3.9
Classifier: Topic :: Scientific/Engineering
Requires-Python: >=3.6
License-File: LICENSE
Requires-Dist: setuptools
Requires-Dist: packaging (>=20.0)
Requires-Dist: typing-extensions (<4.0.0.0,>=3.7.4) ; python_version < "3.8"
